linkedtuple/__init__.py
linkedtuple/linkedtuple.py
linkedtuple-1.0.0.dist-info/LICENSE
linkedtuple-1.0.0.dist-info/METADATA
linkedtuple-1.0.0.dist-info/WHEEL
linkedtuple-1.0.0.dist-info/top_level.txt
linkedtuple-1.0.0.dist-info/RECORD
