Metadata-Version: 2.1
Name: linkedtuple
Version: 1.0.0
Summary: A LinkedTuple is a read-only structure of linked (nested) tuples much like lists in functional languages
Home-page: https://github.com/Gato-X/python-LinkedTuple
Author: Guillermo Romero (Gato-X)
Author-email: gato@felingeneering.com
License: MIT
Platform: UNKNOWN
Classifier: License :: OSI Approved :: MIT License
Classifier: Programming Language :: Python
Classifier: Programming Language :: Python :: 2
Classifier: Programming Language :: Python :: 3
